setup.py
rainbow/__init__.py
rainbow/api.py
rainbow/config.py
rainbow/discover.py
rainbow/server.py
rainbow/settings.py
rainbow/webhandler.py
rainbow/wshandler.py
rainbow/bin/rainbow-server
rainbow/test/__init__.py
rainbow/test/webhandler_test.py
rainbow/test/ws_business_server_test.py
rainbow/test/ws_business_server_test2.py
rainbow/test/ws_client_test.py
rainbow/test/ws_client_test2.py
rainbow/web/__init__.py
rainbow/web/serverinfo.html
rainbow/web/serverinfo.py
rainbow_server.egg-info/PKG-INFO
rainbow_server.egg-info/SOURCES.txt
rainbow_server.egg-info/dependency_links.txt
rainbow_server.egg-info/requires.txt
rainbow_server.egg-info/top_level.txt