Metadata-Version: 1.0
Name: rainbow-server
Version: 0.05
Summary: Rainbow Server Reference Implementation. In Python
Home-page: https://github.com/jeffkit/rainbow
Author: jeff kit
Author-email: bbmyth@gmail.com
License: UNKNOWN
Platform: UNKNOWN
